md_transformer/__init__.py
md_transformer/cli.py
md_transformer/example_transformers.py
md_transformer/mkdocs_plugin.py
md_transformer/render_md.py
md_transformer/transformer.py
md_transformer-0.0.3.dist-info/METADATA
md_transformer-0.0.3.dist-info/WHEEL
md_transformer-0.0.3.dist-info/entry_points.txt
md_transformer-0.0.3.dist-info/licenses/LICENSE.txt
md_transformer-0.0.3.dist-info/RECORD
